{"chunk_definitions":[{"row":25,"row_count":1,"visible":true,"expansion_state":0,"options":{"engine":"r","label":"unnamed-chunk-20","dev":"png"},"document_id":"03155E65","chunk_id":"coji3os50u8ls","chunk_label":"unnamed-chunk-1"},{"row":43,"row_count":1,"visible":true,"expansion_state":0,"options":{"engine":"r","label":"unnamed-chunk-21","dev":"png"},"document_id":"03155E65","chunk_id":"c5kxjq7hekc7d","chunk_label":"unnamed-chunk-2"},{"row":53,"row_count":1,"visible":true,"expansion_state":0,"options":{"engine":"r","label":"unnamed-chunk-22","dev":"png"},"document_id":"03155E65","chunk_id":"cmh9c7nj2ryx3","chunk_label":"unnamed-chunk-3"},{"row":61,"row_count":1,"visible":true,"expansion_state":0,"options":{"engine":"r","label":"unnamed-chunk-25","dev":"png"},"document_id":"03155E65","chunk_id":"cldp67nkweg9y","chunk_label":"unnamed-chunk-4"},{"row":68,"row_count":1,"visible":true,"expansion_state":0,"options":{"engine":"r","label":"unnamed-chunk-27","dev":"png"},"document_id":"03155E65","chunk_id":"cuyyucmypoyxz","chunk_label":"unnamed-chunk-5"},{"row":88,"row_count":1,"visible":true,"expansion_state":0,"options":{"engine":"r","label":"unnamed-chunk-28","dev":"png"},"document_id":"03155E65","chunk_id":"cly19gzyshojb","chunk_label":"unnamed-chunk-6"},{"row":120,"row_count":1,"visible":true,"expansion_state":0,"options":{"engine":"r","label":"unnamed-chunk-29","dev":"png"},"document_id":"03155E65","chunk_id":"c8p8hq28lv6mk","chunk_label":"unnamed-chunk-8"}],"doc_write_time":1743166559}