{"chunk_definitions":[{"row":23,"row_count":1,"visible":true,"expansion_state":0,"options":{"engine":"r","label":"unnamed-chunk-1","dev":"png"},"document_id":"3D1D4054","chunk_id":"cq3ac3xb6rzlz","chunk_label":"unnamed-chunk-1"},{"row":40,"row_count":1,"visible":true,"expansion_state":0,"options":{"engine":"r","label":"unnamed-chunk-33","dev":"png"},"document_id":"3D1D4054","chunk_id":"cq0j68vk9q9nr","chunk_label":"unnamed-chunk-2"},{"row":65,"row_count":1,"visible":true,"expansion_state":0,"options":{"engine":"r","label":"unnamed-chunk-40","dev":"png"},"document_id":"3D1D4054","chunk_id":"cqi98nkrdeheu","chunk_label":"unnamed-chunk-3"},{"row":75,"row_count":1,"visible":true,"expansion_state":0,"options":{"engine":"r","label":"unnamed-chunk-41","dev":"png"},"document_id":"3D1D4054","chunk_id":"c8k23s4nrjoei","chunk_label":"unnamed-chunk-4"},{"row":113,"row_count":1,"visible":true,"expansion_state":0,"options":{"engine":"r","label":"unnamed-chunk-68","dev":"png"},"document_id":"3D1D4054","chunk_id":"csk99625nb9c5","chunk_label":"unnamed-chunk-5"}],"doc_write_time":1743170274}